StellariumRC/__init__.py
StellariumRC/location.py
StellariumRC/locationsearch.py
StellariumRC/main.py
StellariumRC/objects.py
StellariumRC/scripts.py
StellariumRC/simbad.py
StellariumRC/stelaction.py
StellariumRC/stelproperty.py
StellariumRC/view.py
StellariumRC-0.2.dist-info/LICENSE
StellariumRC-0.2.dist-info/METADATA
StellariumRC-0.2.dist-info/WHEEL
StellariumRC-0.2.dist-info/top_level.txt
StellariumRC-0.2.dist-info/RECORD
