Metadata-Version: 2.1
Name: StellariumRC
Version: 0.2
Summary: Control Stellarium by Python
Home-page: https://github.com/k96e/StellariumRC
Author: k96e
Author-email: zy1835562526@gmail.com
License: MIT License
Platform: all
Classifier: Programming Language :: Python :: 3
Classifier: License :: OSI Approved :: MIT License
Classifier: Operating System :: OS Independent
License-File: LICENSE
Requires-Dist: requests
